netupload-0.2.0.dist-info/licenses/LICENSE
src/__init__.py
src/app.py
netupload-0.2.0.dist-info/METADATA
netupload-0.2.0.dist-info/WHEEL
netupload-0.2.0.dist-info/entry_points.txt
netupload-0.2.0.dist-info/top_level.txt
netupload-0.2.0.dist-info/RECORD
