Metadata-Version: 2.4
Name: netupload
Version: 0.2.0
Summary: Simple upload server for local network file transfers.
Home-page: https://github.com/zpg6/netupload
Author: Zach Grimaldi
Classifier: Programming Language :: Python :: 3
Classifier: License :: OSI Approved :: MIT License
License-File: LICENSE
Requires-Dist: Flask==3.0.3
Requires-Dist: Werkzeug==3.0.3
Dynamic: author
Dynamic: classifier
Dynamic: description
Dynamic: description-content-type
Dynamic: home-page
Dynamic: license-file
Dynamic: requires-dist
Dynamic: summary
